{
"type": "FeatureCollection",
"name": "fireSource",
"crs": { "type": "name", "properties": { "name": "urn:ogc:def:crs:OGC:1.3:CRS84" } },
"features": [
{ "type": "Feature", "properties": { "FID": 0 }, "geometry": { "type": "Point", "coordinates": [ -4.683278391051105, 40.463634677147951 ] } }
]
}
